{
  "consumeCatalyst": false,
  "location": "multiblocked:riftway",
  "traits": {},
  "allowRotate": true,
  "showInJei": true,
  "baseRenderer": {
    "modelLocation": "multiblocked:alsm",
    "type": "imodel"
  },
  "formedRenderer": {
    "modelName": "riftway",
    "type": "geo"
  },
  "properties": {
    "isOpaque": false,
    "destroyTime": 1.5,
    "explosionResistance": 6.0,
    "lightEmissive": 0,
    "speedFactor": 1.0,
    "jumpFactor": 1.0,
    "friction": 0.6,
    "hasCollision": true,
    "tabGroup": "multiblocked.all",
    "stackSize": 64
  },
  "basePattern": {
    "structureDir": [
      "RIGHT",
      "UP",
      "FRONT"
    ],
    "pattern": [
      [
        "AAAAA",
        "AAAAA",
        "AAAAA",
        "AAAAA"
      ],
      [
        "AAAAA",
        "AAAAA",
        "AAAAA",
        "AAAAA"
      ],
      [
        "AAAAA",
        "@ACAA",
        "AACAA",
        " AAA "
      ],
      [
        "BBBBB",
        "     ",
        "     ",
        "     "
      ]
    ],
    "aisleRepetitions": [
      [
        1,
        1
      ],
      [
        1,
        1
      ],
      [
        1,
        1
      ],
      [
        1,
        1
      ]
    ],
    "predicates": {
      "A": {
        "blocks": [
          {
            "id": "multiblocked:base"
          }
        ],
        "type": "blocks",
        "disableRenderFormed": true
      },
      "controller": {
        "location": "multiblocked:riftway",
        "type": "component"
      },
      "B": {
        "blocks": [
          {
            "id": "minecraft:smooth_stone_slab"
          }
        ],
        "type": "blocks",
        "disableRenderFormed": true
      },
      "item": {
        "location": "multiblocked:item_hatch",
        "type": "component",
        "disableRenderFormed": true,
        "minCount": 1,
        "maxCount": 1,
        "previewCount": 1
      },
      "star": {
        "location": "multiblocked:sun",
        "type": "component"
      },
      "any": {
        "type": "any"
      },
      "energy": {
        "location": "multiblocked:energy_output",
        "type": "component",
        "disableRenderFormed": true,
        "minCount": 1,
        "maxCount": 1,
        "previewCount": 1
      }
    },
    "symbolMap": {
      "@": [
        "controller"
      ],
      " ": [
        "any"
      ],
      "A": [
        "A",
        "item",
        "energy"
      ],
      "B": [
        "B"
      ],
      "C": [
        "star"
      ]
    }
  },
  "recipeMap": "riftway"
}